fustor_demo/auto_generator.py
fustor_demo/main.py
fustor_demo/mock_agents.py
fustor_demo/store.py
fustor_demo/static/index.html
fustor_demo-0.2.16.dist-info/METADATA
fustor_demo-0.2.16.dist-info/WHEEL
fustor_demo-0.2.16.dist-info/top_level.txt
fustor_demo-0.2.16.dist-info/RECORD
