Metadata-Version: 2.4
Name: fustor-demo
Version: 0.2.16
Summary: Fustor Bio-Fusion Demo for unified directory service
Requires-Python: >=3.11
Requires-Dist: fastapi[all]>=0.104.1
Requires-Dist: uvicorn>=0.23.2
Requires-Dist: fustor-core
Requires-Dist: fustor-event-model
Requires-Dist: pydantic>=2.0.0
Requires-Dist: httpx>=0.25.0
